{
  "updated_at": "2026-06-24T23:59:00.831794+00:00",
  "data": [
    {
      "tx_id": 18661.0,
      "merchant_id": 1628.0,
      "merchant_name": "KOUTE KOUNAYWOLO PARFAIT",
      "district": null,
      "phone": "0585617632",
      "supplier_name": "Sd yssouf Soweto",
      "montant": 658300.0,
      "date_achat": "2026-05-11",
      "maturity_date": "2026-05-25",
      "jours_retard": 30.0,
      "statut": "PENDING",
      "montant_paye": 0.0,
      "montant_restant": 658300.0,
      "latitude": 5.3059962,
      "longitude": -3.9718351,
      "photo_url": null,
      "nb_tx_historique": 12.0,
      "comments": [
        {
          "date": "2026-06-08",
          "type": "COURIER",
          "content": "Date affichée : 2026-06-08 | Commune : Koumassi | Lieu : Koumassi Soweto | Montant total : 574000 | Avance : 500000 | Frais transaction : 25000 | Frais retard : 49000 | Montant payé : 0",
          "author": "evinne"
        },
        {
          "date": "2026-06-03",
          "type": "COURIER",
          "content": "Date affichée : 2026-06-03 | Commune : Koumassi | Lieu : Koumassi Soweto | Montant total : 556500 | Avance : 500000 | Frais transaction : 25000 | Frais retard : 31500 | Montant payé : 0",
          "author": "evinne"
        },
        {
          "date": "2026-06-02",
          "type": "GENERIC_COMMENT",
          "content": "Appel (Sortant) [Recouvrement] : Injoignable",
          "author": "KoneMasse"
        },
        {
          "date": "2026-05-29",
          "type": "GENERIC_COMMENT",
          "content": "Appel (Sortant) [Recouvrement] : Injoignable",
          "author": "evinne"
        },
        {
          "date": "2026-05-28",
          "type": "GENERIC_COMMENT",
          "content": "Appel (Sortant) [Recouvrement] : auucne reponse",
          "author": "evinne"
        },
        {
          "date": "2026-05-26",
          "type": "GENERIC_COMMENT",
          "content": "Appel (Sortant) : aucune reponse",
          "author": "KoneMasse"
        }
      ]
    },
    {
      "tx_id": 19042.0,
      "merchant_id": 2207.0,
      "merchant_name": "KOUADIO Kouame Jean Paul",
      "district": "Yopougon",
      "phone": "+2250709825611",
      "supplier_name": "Socob Locodjro",
      "montant": 850000.0,
      "date_achat": "2026-05-19",
      "maturity_date": "2026-05-26",
      "jours_retard": 29.0,
      "statut": "PENDING",
      "montant_paye": 350000.0,
      "montant_restant": 500000.0,
      "latitude": 5.3176227,
      "longitude": -4.0390803,
      "photo_url": "https://fineract-waribei-transactions-154874852505.s3.eu-north-1.amazonaws.com/documents/98a0b4a50f504e91519d108025682439.jpg",
      "nb_tx_historique": 15.0,
      "comments": [
        {
          "date": "2026-06-17",
          "type": "GENERIC_COMMENT",
          "content": "Appel (Sortant) : il fera le paiement totale lundi et je lui ai demande de faire un paiement partiel cette semaine et le reste le lundi",
          "author": "KoneMasse"
        },
        {
          "date": "2026-06-08",
          "type": "COURIER",
          "content": "Date affichée : 2026-06-08 | Commune : Yopougon | Montant total : 619300 | Avance : 800000 | Frais transaction : 24000 | Frais retard : 55300 | Montant payé : 260000",
          "author": "evinne"
        },
        {
          "date": "2026-06-03",
          "type": "GENERIC_COMMENT",
          "content": "Appel (Sortant) [Recouvrement] : va faire un versement aujourdhui",
          "author": "evinne"
        },
        {
          "date": "2026-06-02",
          "type": "GENERIC_COMMENT",
          "content": "Appel (Sortant) [Recouvrement] : va faire un versement aujourdhui",
          "author": "KoneMasse"
        },
        {
          "date": "2026-05-28",
          "type": "GENERIC_COMMENT",
          "content": "Appel (Sortant) [Recouvrement] : je vais faire un versement aujourdhui",
          "author": "evinne"
        },
        {
          "date": "2026-05-26",
          "type": "GENERIC_COMMENT",
          "content": "Appel (Sortant) [Recouvrement] : demain pour le remboursement",
          "author": "evinne"
        }
      ]
    },
    {
      "tx_id": 19083.0,
      "merchant_id": 2141.0,
      "merchant_name": "MADI ISABELLE AMENAL",
      "district": null,
      "phone": "+2250554505313",
      "supplier_name": "Sd Canaan Port Bouet ",
      "montant": 81100.0,
      "date_achat": "2026-05-19",
      "maturity_date": "2026-05-26",
      "jours_retard": 29.0,
      "statut": "PENDING",
      "montant_paye": 0.0,
      "montant_restant": 81100.0,
      "latitude": 5.2603543,
      "longitude": -3.960027,
      "photo_url": null,
      "nb_tx_historique": 5.0,
      "comments": [
        {
          "date": "2026-06-17",
          "type": "COURIER",
          "content": "Date affichée : 2026-06-17 | Commune : Port-Bouët | Lieu : Port Bouet centre pharmacie malon | Montant total : 36400 | Avance : 30000 | Frais transaction : 1500 | Frais retard : 4900 | Montant payé : 0",
          "author": "KoneMasse"
        },
        {
          "date": "2026-06-09",
          "type": "COURIER",
          "content": "Date affichée : 2026-06-09 | Commune : Port-Bouët | Lieu : Port Bouet centre pharmacie malon | Montant total : 36400 | Avance : 30000 | Frais transaction : 1500 | Frais retard : 4900 | Montant payé : 0",
          "author": "KoneMasse"
        },
        {
          "date": "2026-06-03",
          "type": "GENERIC_COMMENT",
          "content": "Appel (Sortant) [Recouvrement] : recouvrement",
          "author": "evinne"
        },
        {
          "date": "2026-05-28",
          "type": "GENERIC_COMMENT",
          "content": "Appel (Sortant) [Recouvrement] : Injoignable",
          "author": "evinne"
        },
        {
          "date": "2026-05-26",
          "type": "GENERIC_COMMENT",
          "content": "Appel (Sortant) [Recouvrement] : je vais faire ca aujourdhui",
          "author": "evinne"
        }
      ]
    },
    {
      "tx_id": 19068.0,
      "merchant_id": 2710.0,
      "merchant_name": "DIABATE LASSINA",
      "district": "Port-Bouët",
      "phone": "+2250788280631",
      "supplier_name": "Sd sayore Sowetho ",
      "montant": 50000.0,
      "date_achat": "2026-05-19",
      "maturity_date": "2026-05-26",
      "jours_retard": 29.0,
      "statut": "PENDING",
      "montant_paye": 35000.0,
      "montant_restant": 15000.0,
      "latitude": 5.2826197,
      "longitude": -3.9480851,
      "photo_url": "https://fineract-waribei-transactions-154874852505.s3.eu-north-1.amazonaws.com/documents/5ad73057fac0fdc3e24165b5909331c7.jpg",
      "nb_tx_historique": 1.0,
      "comments": [
        {
          "date": "2026-06-19",
          "type": "LETTER_GIVEN_TO_AGENT",
          "content": "RECOUVREMENT : LETTER_GIVEN_TO_AGENT : Appel : Le client signifie qu'il ne vend pas à cause de la pluie qui innonde son coin",
          "author": "francisAka"
        },
        {
          "date": "2026-06-17",
          "type": "COURIER",
          "content": "Date affichée : 2026-06-17 | Commune : Port-Bouët | Lieu : Soweto, hotel baulleme | Montant total : 31400 | Avance : 50000 | Frais transaction : 1500 | Frais retard : 4900 | Montant payé : 25000",
          "author": "KoneMasse"
        },
        {
          "date": "2026-06-09",
          "type": "GENERIC_COMMENT",
          "content": "Message (Entrant) : après avoir reçu son courrier: Bonsoir monsieur madame \nComment vas-tu ?\n\nJe comprends votre réaction, mais je vous demande simplement un peu de patience. Je n’ai jamais dit que je ne paierais pas et je compte bien vous rembourser. La situation est compliquée en ce moment, mais je fais le nécessaire pour trouver une solution rapidement. J’aimerais qu’on puisse garder un dialogue calme et éviter de couper les négociations, car mon intention reste de régler cela correctement.",
          "author": "KoneMasse"
        },
        {
          "date": "2026-06-09",
          "type": "COURIER",
          "content": "Date affichée : 2026-06-09 | Commune : Port-Bouët | Lieu : Soweto, hotel baulleme | Montant total : 56400 | Avance : 50000 | Frais transaction : 1500 | Frais retard : 4900 | Montant payé : 0",
          "author": "KoneMasse"
        },
        {
          "date": "2026-06-08",
          "type": "COURIER",
          "content": "Date affichée : 2026-06-08 | Commune : Port-Bouët | Lieu : Soweto, hotel baulleme | Montant total : 56050 | Avance : 50000 | Frais transaction : 1500 | Frais retard : 4550 | Montant payé : 0",
          "author": "evinne"
        },
        {
          "date": "2026-06-03",
          "type": "GENERIC_COMMENT",
          "content": "Appel (Sortant) [Recouvrement] : recouvrement",
          "author": "evinne"
        },
        {
          "date": "2026-05-28",
          "type": "GENERIC_COMMENT",
          "content": "Appel (Sortant) [Recouvrement] : il le fera ce soir",
          "author": "evinne"
        },
        {
          "date": "2026-05-26",
          "type": "GENERIC_COMMENT",
          "content": "Appel (Sortant) : il le fera ce soir",
          "author": "KoneMasse"
        }
      ]
    },
    {
      "tx_id": 19202.0,
      "merchant_id": 2506.0,
      "merchant_name": "GUIAGUI SERY WILFRED",
      "district": "Port-Bouët",
      "phone": "+2250777108124",
      "supplier_name": "Sd sportif ",
      "montant": 225200.0,
      "date_achat": "2026-05-21",
      "maturity_date": "2026-05-28",
      "jours_retard": 27.0,
      "statut": "PENDING",
      "montant_paye": 80500.0,
      "montant_restant": 144700.0,
      "latitude": 5.2482423,
      "longitude": -3.9088062,
      "photo_url": "https://fineract-waribei-transactions-154874852505.s3.eu-north-1.amazonaws.com/documents/00b20c51fc88cd7a4750aafa31db668f.jpg",
      "nb_tx_historique": 4.0,
      "comments": [
        {
          "date": "2026-06-22",
          "type": "COURIER",
          "content": "Date affichée : 2026-06-22 | Commune : Port-Bouët | Lieu : Gonzague mobibois carrefour Jannot | Montant total : 30200 | Avance : 100000 | Frais transaction : 3000 | Frais retard : 7700 | Montant payé : 80500",
          "author": "evinne"
        },
        {
          "date": "2026-06-17",
          "type": "COURIER",
          "content": "Date affichée : 2026-06-17 | Commune : Port-Bouët | Lieu : Gonzague mobibois carrefour Jannot | Montant total : 30200 | Avance : 100000 | Frais transaction : 3000 | Frais retard : 7700 | Montant payé : 80500",
          "author": "KoneMasse"
        },
        {
          "date": "2026-06-09",
          "type": "COURIER",
          "content": "Date affichée : 2026-06-09 | Commune : Port-Bouët | Lieu : Gonzague mobibois carrefour Jannot | Montant total : 60000 | Avance : 100000 | Frais transaction : 3000 | Frais retard : 7000 | Montant payé : 50000",
          "author": "KoneMasse"
        },
        {
          "date": "2026-06-08",
          "type": "COURIER",
          "content": "Date affichée : 2026-06-08 | Commune : Port-Bouët | Lieu : Gonzague mobibois carrefour Jannot | Montant total : 59650 | Avance : 100000 | Frais transaction : 3000 | Frais retard : 6650 | Montant payé : 50000",
          "author": "evinne"
        },
        {
          "date": "2026-06-03",
          "type": "GENERIC_COMMENT",
          "content": "Appel:03-06-2026:18-07:00:00:Oui, allez, bonsoir, monsieur. Oui, mais pourquoi? C'est Waribe. Comment? C'est Waribe, Waribe. Oui, oui, oui, oui. Monsieur, je vais vous appeler par rapport au remboursement. Oui, je n'ai pas oublié, il y a eu un contrat de travail. Vous avez un collègue qui est sur le terrain ici, là. D'accord. Je ne vais pas appeler. Non, je sais, je connais toute l'équipe. C'est parce que c'est délicat, tout. A part que demain, je vais commencer à payer un peu. Parce qu'il y a eu un contrat de travail. Je suis parti en voyage. A 100 millions d'IRM, ils ont foutu la main. Donc, on m'a mis dans le problème. Mais j'endorse la responsabilité parce qu'il y a des taxes qui payent un peu, un peu. Les taxes, c'est que ça suffit. Donc, à partir de demain, je vais commencer à effectuer le paiement. Ok, c'est compris, monsieur. D'accord. Ok, merci bien. Merci.:Recouvrement",
          "author": "evinne"
        },
        {
          "date": "2026-06-03",
          "type": "GENERIC_COMMENT",
          "content": "Appel (Sortant) [Recouvrement] : aucune reponse",
          "author": "evinne"
        },
        {
          "date": "2026-05-28",
          "type": "GENERIC_COMMENT",
          "content": "Appel (Sortant) : il est a une cérémonie présentement quand il rentre il fera le versement",
          "author": "KoneMasse"
        }
      ]
    },
    {
      "tx_id": 18871.0,
      "merchant_id": 1117.0,
      "merchant_name": "BEUGRE AGOUA DANIELLE LARISSA",
      "district": null,
      "phone": "+2250758637769",
      "supplier_name": "Sd yssouf Soweto",
      "montant": 657950.0,
      "date_achat": "2026-05-15",
      "maturity_date": "2026-05-29",
      "jours_retard": 26.0,
      "statut": "PENDING",
      "montant_paye": 490100.0,
      "montant_restant": 167850.0,
      "latitude": 5.3102021,
      "longitude": -3.9700283,
      "photo_url": null,
      "nb_tx_historique": 11.0,
      "comments": [
        {
          "date": "2026-06-22",
          "type": "COURIER",
          "content": "Date affichée : 2026-06-22 | Commune : Marcory | Lieu : Marcory, anoumanbo, carrefour amangou (fromager) | Montant total : 219700 | Avance : 650000 | Frais transaction : 32500 | Frais retard : 27300 | Montant payé : 490100",
          "author": "evinne"
        },
        {
          "date": "2026-06-17",
          "type": "GENERIC_COMMENT",
          "content": "Appel (Sortant) [Recouvrement] : elle a perdu sa mère et ses gérants sont en compositions pour le bac donc le dépôt est ferme présentement il sera ouvert ce Week end et la semaine prochaine elle fera des paiement partiels pour solder",
          "author": "KoneMasse"
        },
        {
          "date": "2026-06-17",
          "type": "COURIER",
          "content": "Date affichée : 2026-06-17 | Commune : Marcory | Lieu : Marcory, anoumanbo, carrefour amangou (fromager) | Montant total : 219700 | Avance : 650000 | Frais transaction : 32500 | Frais retard : 27300 | Montant payé : 490100",
          "author": "KoneMasse"
        },
        {
          "date": "2026-06-08",
          "type": "COURIER",
          "content": "Date affichée : 2026-06-08 | Commune : Marcory | Lieu : Marcory, anoumanbo, carrefour amangou (fromager) | Montant total : 292900 | Avance : 650000 | Frais transaction : 32500 | Frais retard : 21700 | Montant payé : 411300",
          "author": "evinne"
        },
        {
          "date": "2026-06-03",
          "type": "GENERIC_COMMENT",
          "content": "Appel (Sortant) [Recouvrement] : elle va faire un versement",
          "author": "evinne"
        },
        {
          "date": "2026-06-02",
          "type": "GENERIC_COMMENT",
          "content": "Appel (Sortant) [Recouvrement] : son livreur dit qu elle est sortir ai demande de lui dire de nous rappeler",
          "author": "KoneMasse"
        },
        {
          "date": "2026-06-02",
          "type": "GENERIC_COMMENT",
          "content": "Appel (Sortant) [Recouvrement] : aucune reponse",
          "author": "KoneMasse"
        },
        {
          "date": "2026-05-29",
          "type": "GENERIC_COMMENT",
          "content": "Appel (Sortant) : aucune reponse",
          "author": "KoneMasse"
        }
      ]
    },
    {
      "tx_id": 19228.0,
      "merchant_id": 1289.0,
      "merchant_name": "DANZO MAMI HERMANCE",
      "district": "Cocody",
      "phone": "+2250709462399",
      "supplier_name": "Dépôt Redis angré",
      "montant": 200000.0,
      "date_achat": "2026-05-22",
      "maturity_date": "2026-05-29",
      "jours_retard": 26.0,
      "statut": "PENDING",
      "montant_paye": 59000.0,
      "montant_restant": 141000.0,
      "latitude": 5.3746951,
      "longitude": -3.9742912,
      "photo_url": "https://fineract-waribei-transactions-154874852505.s3.eu-north-1.amazonaws.com/documents/8f353781cc1638e550f52b114eae3193.jpg",
      "nb_tx_historique": 13.0,
      "comments": [
        {
          "date": "2026-06-17",
          "type": "GENERIC_COMMENT",
          "content": "Appel (Sortant) : elle etait au CHU avec son fils qui etait gravement malade depuis quelques semaines et elle est rentre hier seulement de l'hôpital je lui ai demander de regler la totalité avant la semaine prochaine",
          "author": "KoneMasse"
        },
        {
          "date": "2026-06-08",
          "type": "COURIER",
          "content": "Date affichée : 2026-06-08 | Commune : Cocody | Lieu : Bonoumin , cité laurier 6 | Montant total : 157850 | Avance : 200000 | Frais transaction : 6000 | Frais retard : 10850 | Montant payé : 59000",
          "author": "evinne"
        },
        {
          "date": "2026-06-03",
          "type": "GENERIC_COMMENT",
          "content": "Appel (Sortant) [Recouvrement] : aucune reponse",
          "author": "evinne"
        },
        {
          "date": "2026-05-29",
          "type": "GENERIC_COMMENT",
          "content": "Appel (Sortant) : elle fera une partie paiement ce soir et le reste demain",
          "author": "KoneMasse"
        }
      ]
    },
    {
      "tx_id": 19232.0,
      "merchant_id": 2712.0,
      "merchant_name": "GBAMA TANGUY PRINCE JUNIOR",
      "district": "Cocody",
      "phone": "+2250749694425",
      "supplier_name": "SD Brou Abobo",
      "montant": 53150.0,
      "date_achat": "2026-05-22",
      "maturity_date": "2026-05-29",
      "jours_retard": 26.0,
      "statut": "PENDING",
      "montant_paye": 40000.0,
      "montant_restant": 13150.0,
      "latitude": 5.4008255,
      "longitude": -3.9377463,
      "photo_url": "https://fineract-waribei-transactions-154874852505.s3.eu-north-1.amazonaws.com/documents/0dd2437417246cabf050625777979c98.jpg",
      "nb_tx_historique": 1.0,
      "comments": [
        {
          "date": "2026-06-22",
          "type": "COURIER",
          "content": "Date affichée : 2026-06-22 | Commune : Cocody | Lieu : Djorobité 1 carrefour dramer | Montant total : 16400 | Avance : 50000 | Frais transaction : 1500 | Frais retard : 4900 | Montant payé : 40000",
          "author": "evinne"
        },
        {
          "date": "2026-06-03",
          "type": "GENERIC_COMMENT",
          "content": "Appel (Sortant) [Recouvrement] : va faire un versement aujours",
          "author": "evinne"
        },
        {
          "date": "2026-05-29",
          "type": "GENERIC_COMMENT",
          "content": "Appel (Sortant) : il fera son paiement toute toute a l'heure",
          "author": "KoneMasse"
        }
      ]
    },
    {
      "tx_id": 19237.0,
      "merchant_id": 2018.0,
      "merchant_name": "AMISSAH AMA SOPHIE IRELLE",
      "district": null,
      "phone": "+2250779729440",
      "supplier_name": "Dépôt Zoro-bi Bassam",
      "montant": 50000.0,
      "date_achat": "2026-05-22",
      "maturity_date": "2026-05-29",
      "jours_retard": 26.0,
      "statut": "PENDING",
      "montant_paye": 29600.0,
      "montant_restant": 20400.0,
      "latitude": 5.464815,
      "longitude": -3.2098813,
      "photo_url": null,
      "nb_tx_historique": 15.0,
      "comments": [
        {
          "date": "2026-06-22",
          "type": "COURIER",
          "content": "Date affichée : 2026-06-22 | Commune : Grand Bassam | Lieu : Bassam ancien réseau | Montant total : 26800 | Avance : 50000 | Frais transaction : 1500 | Frais retard : 4900 | Montant payé : 29600",
          "author": "evinne"
        },
        {
          "date": "2026-06-22",
          "type": "COURIER",
          "content": "Date affichée : 2026-06-22 | Commune : Grand Bassam | Lieu : Bassam ancien réseau | Montant total : 26800 | Avance : 50000 | Frais transaction : 1500 | Frais retard : 4900 | Montant payé : 29600",
          "author": "evinne"
        },
        {
          "date": "2026-06-17",
          "type": "GENERIC_COMMENT",
          "content": "Appel (Sortant) [Recouvrement] : son espace est car elle est a l'INFAS présentement et sa sœur qui gérait l'espace est aussi en composition pour le bac .elle dit pouvoir payer la totalité jusqu'au vendredi",
          "author": "KoneMasse"
        },
        {
          "date": "2026-06-17",
          "type": "COURIER",
          "content": "Date affichée : 2026-06-17 | Commune : Grand Bassam | Lieu : Bassam ancien réseau | Montant total : 31800 | Avance : 50000 | Frais transaction : 1500 | Frais retard : 4900 | Montant payé : 24600",
          "author": "KoneMasse"
        },
        {
          "date": "2026-06-09",
          "type": "COURIER",
          "content": "Date affichée : 2026-06-09 | Commune : Grand Bassam | Lieu : Bassam ancien réseau | Montant total : 32750 | Avance : 50000 | Frais transaction : 1500 | Frais retard : 3850 | Montant payé : 22600",
          "author": "KoneMasse"
        },
        {
          "date": "2026-06-08",
          "type": "COURIER",
          "content": "Date affichée : 2026-06-08 | Commune : Grand Bassam | Lieu : Bassam ancien réseau | Montant total : 32400 | Avance : 50000 | Frais transaction : 1500 | Frais retard : 3500 | Montant payé : 22600",
          "author": "evinne"
        },
        {
          "date": "2026-06-03",
          "type": "GENERIC_COMMENT",
          "content": "Appel (Sortant) [Recouvrement] : va faire un versement aujourdhui",
          "author": "evinne"
        },
        {
          "date": "2026-05-29",
          "type": "GENERIC_COMMENT",
          "content": "Appel (Sortant) : elle fera une partie du paiement ce soir et le reste demain car le marche est lent a cause de la pluie",
          "author": "KoneMasse"
        }
      ]
    },
    {
      "tx_id": 19260.0,
      "merchant_id": 2683.0,
      "merchant_name": "DJESSAN BILOPOA MARTIAL",
      "district": "Yopougon",
      "phone": "2250702082679",
      "supplier_name": "Socob Locodjro",
      "montant": 471650.0,
      "date_achat": "2026-05-23",
      "maturity_date": "2026-05-30",
      "jours_retard": 25.0,
      "statut": "PENDING",
      "montant_paye": 100000.0,
      "montant_restant": 371650.0,
      "latitude": 5.3315492,
      "longitude": -4.0769954,
      "photo_url": "https://fineract-waribei-transactions-154874852505.s3.eu-north-1.amazonaws.com/documents/ab61988dab2481ec731f3401d6d0f913.jpg",
      "nb_tx_historique": 2.0,
      "comments": [
        {
          "date": "2026-06-22",
          "type": "COURIER",
          "content": "Date affichée : 2026-06-22 | Commune : Yopougon | Lieu : A côté de la pharmacie lem | Montant total : 424900 | Avance : 470000 | Frais transaction : 15000 | Frais retard : 39900 | Montant payé : 100000",
          "author": "evinne"
        },
        {
          "date": "2026-06-17",
          "type": "GENERIC_COMMENT",
          "content": "Appel (Sortant) [Recouvrement] : il dit avoir ete victime de cambriolage et qu'il a essayer de prendre un pret dans une autre banque mais il lui ont dit qu'il n'etais pas sovable car il doit waribei .il dit qu'il fera son paiement dans ls jours a venir",
          "author": "KoneMasse"
        },
        {
          "date": "2026-06-17",
          "type": "COURIER",
          "content": "Date affichée : 2026-06-17 | Commune : Yopougon | Lieu : A côté de la pharmacie lem | Montant total : 424900 | Avance : 470000 | Frais transaction : 15000 | Frais retard : 39900 | Montant payé : 100000",
          "author": "KoneMasse"
        },
        {
          "date": "2026-06-08",
          "type": "COURIER",
          "content": "Date affichée : 2026-06-08 | Commune : Yopougon | Lieu : A côté de la pharmacie lem | Montant total : 410900 | Avance : 470000 | Frais transaction : 15000 | Frais retard : 25900 | Montant payé : 100000",
          "author": "evinne"
        },
        {
          "date": "2026-06-02",
          "type": "GENERIC_COMMENT",
          "content": "Appel (Sortant) [Recouvrement] : aucune reponse",
          "author": "KoneMasse"
        }
      ]
    },
    {
      "tx_id": 19269.0,
      "merchant_id": 945.0,
      "merchant_name": "Sylvie Rosette KOUAME",
      "district": null,
      "phone": "+2250779581035",
      "supplier_name": "NBF Distribution",
      "montant": 200000.0,
      "date_achat": "2026-05-23",
      "maturity_date": "2026-05-30",
      "jours_retard": 25.0,
      "statut": "PENDING",
      "montant_paye": 145400.0,
      "montant_restant": 54600.0,
      "latitude": 5.3454092,
      "longitude": -4.1122905,
      "photo_url": null,
      "nb_tx_historique": 55.0,
      "comments": [
        {
          "date": "2026-06-22",
          "type": "COURIER",
          "content": "Date affichée : 2026-06-22 | Montant total : 128800 | Avance : 200000 | Frais transaction : 6000 | Frais retard : 18200 | Montant payé : 95400",
          "author": "evinne"
        },
        {
          "date": "2026-06-17",
          "type": "COURIER",
          "content": "Date affichée : 2026-06-17 | Montant total : 148800 | Avance : 200000 | Frais transaction : 6000 | Frais retard : 18200 | Montant payé : 75400",
          "author": "KoneMasse"
        },
        {
          "date": "2026-06-17",
          "type": "COURIER",
          "content": "Date affichée : 2026-06-17 | Montant total : 158800 | Avance : 200000 | Frais transaction : 6000 | Frais retard : 18200 | Montant payé : 65400",
          "author": "KoneMasse"
        },
        {
          "date": "2026-06-08",
          "type": "COURIER",
          "content": "Date affichée : 2026-06-08 | Montant total : 178200 | Avance : 200000 | Frais transaction : 6000 | Frais retard : 12600 | Montant payé : 40400",
          "author": "evinne"
        },
        {
          "date": "2026-06-03",
          "type": "GENERIC_COMMENT",
          "content": "Appel:03-06-2026:18-21:02:29:Allo, bonsoir madame, c'est Waribe, vous appelez papa au remboursement, ça fait 4 jours aujourd'hui. Bon, le fournisseur a dit que le truc n'allait pas bien et qu'il fallait que tu l'amènes à papa. Comment? Le fournisseur dit quoi? Bon, le fournisseur... Allo? Oui, allo monsieur. Oui madame, vous dites que le fournisseur vous a dit quoi? Le réseau ne passait pas sa maidie, donc j'étais obligée de payer avec l'argent. C'est à cause de ça que je n'ai pas pu rembourser. Donc j'ai appelé le fournisseur pour lui dire ça. Je n'arrivais pas à faire tout. Donc j'étais obligée de payer avec l'argent. Je ne comprends pas, c'est-à-dire que vous n'arrivez pas à payer avec l'application? Oui. Donc c'est pour ça qu'au lieu de nous appeler, vous avez appelé le fournisseur? Oui, oui. Mais madame, c'est nous que vous devez, ce n'est pas le fournisseur. Donc c'est nous que vous aurez dû appeler? Comme d'habitude, c'est lui que j'ai fait. Donc quand vous lui avez dit, c'est lui qui a dit de payer directement au lieu de passer par moi? Oui, oui. C'est lui qui vous a dit ça? Non, puisqu'il n'y avait pas de boisson, donc j'ai commandé la boisson. Au fait, j'ai payé cash quoi. Vous avez pris l'argent pour payer cash sur votre fournisseur au lieu de rembourser ici? Oui. Bon, faire comment? Parce que là, ça fait 4 jours de retard. À partir de demain, je vais payer. Demain, je vais payer. Demain, vous allez payer la totalité, c'est ça? Non, non. Plus que ça, ma vie est faite. Non, mais ça, ce n'est pas de notre côté en fait. Je ne sais pas si vous comprenez ce que j'ai dit. Oui, je comprends ce que vous dites. Une fois que vous payez ça, c'est quoi? On arrête ou bien vous allez voir avec le fournisseur d'abord avant de reprendre? Je vais voir avec le fournisseur avant de reprendre. D'accord, ok. Donc à demain. D'accord, d'accord.:Recouvrement",
          "author": "evinne"
        }
      ]
    },
    {
      "tx_id": 19262.0,
      "merchant_id": 2178.0,
      "merchant_name": "N'KAYO MANDJI LAURE ELIANE",
      "district": null,
      "phone": "+2250141646434",
      "supplier_name": "Sd Emmanuella anokoi koute",
      "montant": 120000.0,
      "date_achat": "2026-05-23",
      "maturity_date": "2026-05-30",
      "jours_retard": 25.0,
      "statut": "PENDING",
      "montant_paye": 120000.0,
      "montant_restant": 0.0,
      "latitude": 5.4375013,
      "longitude": -4.0449159,
      "photo_url": null,
      "nb_tx_historique": 15.0,
      "comments": [
        {
          "date": "2026-06-22",
          "type": "COURIER",
          "content": "Date affichée : 2026-06-22 | Commune : Abobo | Lieu : Anonkoi Kouté | Montant total : 32450 | Avance : 120000 | Frais transaction : 4500 | Frais retard : 12950 | Montant payé : 105000",
          "author": "evinne"
        },
        {
          "date": "2026-06-08",
          "type": "COURIER",
          "content": "Date affichée : 2026-06-08 | Commune : Abobo | Lieu : Anonkoi Kouté | Montant total : 88950 | Avance : 120000 | Frais transaction : 4500 | Frais retard : 9450 | Montant payé : 45000",
          "author": "evinne"
        },
        {
          "date": "2026-06-03",
          "type": "GENERIC_COMMENT",
          "content": "Appel (Sortant) [Recouvrement] : indisponible",
          "author": "evinne"
        }
      ]
    },
    {
      "tx_id": 19270.0,
      "merchant_id": 2515.0,
      "merchant_name": "BEUGRE LEGA STEPHANIE COLOMBE",
      "district": "Yopougon",
      "phone": "002250152471412",
      "supplier_name": "Socob Locodjro",
      "montant": 99000.0,
      "date_achat": "2026-05-23",
      "maturity_date": "2026-05-30",
      "jours_retard": 25.0,
      "statut": "PENDING",
      "montant_paye": 0.0,
      "montant_restant": 99000.0,
      "latitude": 5.3131273,
      "longitude": -4.0443644,
      "photo_url": "https://fineract-waribei-transactions-154874852505.s3.eu-north-1.amazonaws.com/documents/b9bdd28e4a022b0feb648f473312676d.jpg",
      "nb_tx_historique": 6.0,
      "comments": [
        {
          "date": "2026-06-22",
          "type": "COURIER",
          "content": "Date affichée : 2026-06-22 | Commune : Yopougon | Lieu : Toits rouge | Montant total : 92800 | Avance : 80000 | Frais transaction : 3000 | Frais retard : 9800 | Montant payé : 0",
          "author": "evinne"
        },
        {
          "date": "2026-06-22",
          "type": "COURIER",
          "content": "Date affichée : 2026-06-22 | Commune : Yopougon | Lieu : Toits rouge | Montant total : 92800 | Avance : 80000 | Frais transaction : 3000 | Frais retard : 9800 | Montant payé : 0",
          "author": "evinne"
        },
        {
          "date": "2026-06-17",
          "type": "COURIER",
          "content": "Date affichée : 2026-06-17 | Commune : Yopougon | Lieu : Toits rouge | Montant total : 92800 | Avance : 80000 | Frais transaction : 3000 | Frais retard : 9800 | Montant payé : 0",
          "author": "KoneMasse"
        },
        {
          "date": "2026-06-16",
          "type": "COURIER",
          "content": "Date affichée : 2026-06-16 | Commune : Yopougon | Lieu : Toits rouge | Montant total : 92800 | Avance : 80000 | Frais transaction : 3000 | Frais retard : 9800 | Montant payé : 0",
          "author": "KoneMasse"
        },
        {
          "date": "2026-06-08",
          "type": "COURIER",
          "content": "Date affichée : 2026-06-08 | Commune : Yopougon | Lieu : Toits rouge | Montant total : 89300 | Avance : 80000 | Frais transaction : 3000 | Frais retard : 6300 | Montant payé : 0",
          "author": "evinne"
        }
      ]
    },
    {
      "tx_id": 19312.0,
      "merchant_id": 116.0,
      "merchant_name": "Gondy Minkapet Stephane DETI",
      "district": null,
      "phone": "2250759753851",
      "supplier_name": "Dépôt Redis angré",
      "montant": 97500.0,
      "date_achat": "2026-05-23",
      "maturity_date": "2026-05-30",
      "jours_retard": 25.0,
      "statut": "PENDING",
      "montant_paye": 0.0,
      "montant_restant": 97500.0,
      "latitude": 5.3883509,
      "longitude": -4.0002468,
      "photo_url": null,
      "nb_tx_historique": 55.0,
      "comments": [
        {
          "date": "2026-06-22",
          "type": "COURIER",
          "content": "Date affichée : 2026-06-22 | Montant total : 110300 | Avance : 97500 | Frais transaction : 3000 | Frais retard : 9800 | Montant payé : 0",
          "author": "evinne"
        },
        {
          "date": "2026-06-22",
          "type": "COURIER",
          "content": "Date affichée : 2026-06-22 | Montant total : 110300 | Avance : 97500 | Frais transaction : 3000 | Frais retard : 9800 | Montant payé : 0",
          "author": "KoneMasse"
        },
        {
          "date": "2026-06-08",
          "type": "COURIER",
          "content": "Date affichée : 2026-06-08 | Montant total : 106800 | Avance : 97500 | Frais transaction : 3000 | Frais retard : 6300 | Montant payé : 0",
          "author": "evinne"
        }
      ]
    },
    {
      "tx_id": 19363.0,
      "merchant_id": 2629.0,
      "merchant_name": "DIETH JEAN FERNAND SHILTON",
      "district": "Treichville",
      "phone": "+2250101137226",
      "supplier_name": "Sd 2ke Multi service Treichville ",
      "montant": 158250.0,
      "date_achat": "2026-05-24",
      "maturity_date": "2026-05-31",
      "jours_retard": 24.0,
      "statut": "PENDING",
      "montant_paye": 59000.0,
      "montant_restant": 99250.0,
      "latitude": 5.3035546,
      "longitude": -3.9984069,
      "photo_url": "https://fineract-waribei-transactions-154874852505.s3.eu-north-1.amazonaws.com/documents/c3ac1ede1616603f1680f940594ebce8.jpg",
      "nb_tx_historique": 3.0,
      "comments": [
        {
          "date": "2026-06-24",
          "type": "COURIER",
          "content": "Date affichée : 2026-06-24 | Commune : Treichville | Lieu : Radio Jam | Montant total : 110200 | Avance : 150000 | Frais transaction : 4500 | Frais retard : 14700 | Montant payé : 59000",
          "author": "KoneMasse"
        },
        {
          "date": "2026-06-23",
          "type": "GENERIC_COMMENT",
          "content": "Appel (Sortant) [Recouvrement] : il fera des paiements de 14mille tout les jours",
          "author": "KoneMasse"
        },
        {
          "date": "2026-06-22",
          "type": "COURIER",
          "content": "Date affichée : 2026-06-22 | Commune : Treichville | Lieu : Radio Jam | Montant total : 124200 | Avance : 150000 | Frais transaction : 4500 | Frais retard : 14700 | Montant payé : 45000",
          "author": "evinne"
        },
        {
          "date": "2026-06-08",
          "type": "GENERIC_COMMENT",
          "content": "Appel (Sortant) [Recouvrement] : aucune reponse",
          "author": "evinne"
        },
        {
          "date": "2026-06-08",
          "type": "COURIER",
          "content": "Date affichée : 2026-06-08 | Commune : Treichville | Lieu : Radio Jam | Montant total : 117900 | Avance : 150000 | Frais transaction : 4500 | Frais retard : 8400 | Montant payé : 45000",
          "author": "evinne"
        },
        {
          "date": "2026-06-01",
          "type": "GENERIC_COMMENT",
          "content": "Message (Entrant) : Mes serveuses sont malades et elles n'ont pas pu travailler convenablement",
          "author": "KoneMasse"
        },
        {
          "date": "2026-06-01",
          "type": "GENERIC_COMMENT",
          "content": "Message (Entrant) : Bonjour, j'accuserai un retard de 3 jours à compter d'aujourd'hui sur mon remboursement en cours, cordialement",
          "author": "KoneMasse"
        }
      ]
    },
    {
      "tx_id": 19368.0,
      "merchant_id": 2122.0,
      "merchant_name": "EHOUE DANIEL CHABOREL",
      "district": "Yopougon",
      "phone": "+2250708337447",
      "supplier_name": "Sd Guyzo Selmer ",
      "montant": 150000.0,
      "date_achat": "2026-05-24",
      "maturity_date": "2026-05-31",
      "jours_retard": 24.0,
      "statut": "PENDING",
      "montant_paye": 0.0,
      "montant_restant": 150000.0,
      "latitude": 5.3545823,
      "longitude": -4.0747206,
      "photo_url": "https://fineract-waribei-transactions-154874852505.s3.eu-north-1.amazonaws.com/documents/c8c296c9d242a33f04ed2673ec1be8f1.jpg",
      "nb_tx_historique": 2.0,
      "comments": [
        {
          "date": "2026-06-22",
          "type": "COURIER",
          "content": "Date affichée : 2026-06-22 | Commune : Yopougon | Lieu : Siporex | Montant total : 169200 | Avance : 150000 | Frais transaction : 4500 | Frais retard : 14700 | Montant payé : 0",
          "author": "evinne"
        },
        {
          "date": "2026-06-08",
          "type": "GENERIC_COMMENT",
          "content": "Appel (Sortant) [Recouvrement] : les casses ont fait qu il ne peux pas rembourser et quil a prevenu djamila",
          "author": "evinne"
        },
        {
          "date": "2026-06-08",
          "type": "COURIER",
          "content": "Date affichée : 2026-06-08 | Commune : Yopougon | Lieu : Siporex | Montant total : 162900 | Avance : 150000 | Frais transaction : 4500 | Frais retard : 8400 | Montant payé : 0",
          "author": "evinne"
        }
      ]
    },
    {
      "tx_id": 19424.0,
      "merchant_id": 2641.0,
      "merchant_name": "EDOUKOU KOUAKOU MICHAEL",
      "district": "Abobo",
      "phone": "2250778340433",
      "supplier_name": "Sd Angélique abobo",
      "montant": 305100.0,
      "date_achat": "2026-05-25",
      "maturity_date": "2026-06-01",
      "jours_retard": 23.0,
      "statut": "PENDING",
      "montant_paye": 200000.0,
      "montant_restant": 105100.0,
      "latitude": 5.4353384,
      "longitude": -4.00908,
      "photo_url": "https://fineract-waribei-transactions-154874852505.s3.eu-north-1.amazonaws.com/documents/0923013351880284bcefa10317f597da.jpg",
      "nb_tx_historique": 3.0,
      "comments": [
        {
          "date": "2026-06-16",
          "type": "COURIER",
          "content": "Date affichée : 2026-06-16 | Commune : Abobo | Lieu : Soghefia | Montant total : 131400 | Avance : 300000 | Frais transaction : 9000 | Frais retard : 22400 | Montant payé : 200000",
          "author": "KoneMasse"
        },
        {
          "date": "2026-06-08",
          "type": "GENERIC_COMMENT",
          "content": "Appel (Sortant) [Recouvrement] : auucne reponse",
          "author": "evinne"
        },
        {
          "date": "2026-06-08",
          "type": "COURIER",
          "content": "Date affichée : 2026-06-08 | Commune : Abobo | Lieu : Soghefia | Montant total : 323700 | Avance : 300000 | Frais transaction : 9000 | Frais retard : 14700 | Montant payé : 0",
          "author": "evinne"
        },
        {
          "date": "2026-06-04",
          "type": "GENERIC_COMMENT",
          "content": "Appel (Sortant) [Recouvrement] : il a va faire ca aujourdhui",
          "author": "evinne"
        }
      ]
    },
    {
      "tx_id": 19415.0,
      "merchant_id": 2582.0,
      "merchant_name": "GOUSSEBOTIN GAEL RODRIGUE",
      "district": "Yopougon",
      "phone": "+2250747936742",
      "supplier_name": "Socob Locodjro",
      "montant": 101925.0,
      "date_achat": "2026-05-25",
      "maturity_date": "2026-06-01",
      "jours_retard": 23.0,
      "statut": "PENDING",
      "montant_paye": 0.0,
      "montant_restant": 101925.0,
      "latitude": 5.3235922,
      "longitude": -4.0628157,
      "photo_url": "https://fineract-waribei-transactions-154874852505.s3.eu-north-1.amazonaws.com/documents/90c5e85757def072b4a57fe6ad13bcf4.jpg",
      "nb_tx_historique": 3.0,
      "comments": [
        {
          "date": "2026-06-17",
          "type": "GENERIC_COMMENT",
          "content": "Appel (Sortant) [Recouvrement] : aucune reponse",
          "author": "KoneMasse"
        },
        {
          "date": "2026-06-17",
          "type": "COURIER",
          "content": "Date affichée : 2026-06-17 | Commune : Yopougon | Lieu : Petit toit rouge au virage | Montant total : 112800 | Avance : 100000 | Frais transaction : 3000 | Frais retard : 9800 | Montant payé : 0",
          "author": "KoneMasse"
        },
        {
          "date": "2026-06-08",
          "type": "COURIER",
          "content": "Date affichée : 2026-06-08 | Commune : Yopougon | Lieu : Petit toit rouge au virage | Montant total : 107900 | Avance : 100000 | Frais transaction : 3000 | Frais retard : 4900 | Montant payé : 0",
          "author": "evinne"
        },
        {
          "date": "2026-06-04",
          "type": "GENERIC_COMMENT",
          "content": "Appel (Sortant) [Recouvrement] : il va faire le necessaire jusqua la fin de la semaine car ses vendeurs ont vendu mais ils sont pas la",
          "author": "evinne"
        },
        {
          "date": "2026-05-30",
          "type": "GENERIC_COMMENT",
          "content": "Appel (Entrant) : il aura du retard car son gérant a fui avec sa recette quand il était en voyage ",
          "author": "KoneMasse"
        }
      ]
    },
    {
      "tx_id": 19072.0,
      "merchant_id": 2286.0,
      "merchant_name": "ANGBOH RODRIGUE",
      "district": "Yopougon",
      "phone": "+2250758805121",
      "supplier_name": "NCDI.S ",
      "montant": 663650.0,
      "date_achat": "2026-05-19",
      "maturity_date": "2026-06-02",
      "jours_retard": 22.0,
      "statut": "PENDING",
      "montant_paye": 319800.0,
      "montant_restant": 343850.0,
      "latitude": 5.3150432,
      "longitude": -4.0944473,
      "photo_url": "https://fineract-waribei-transactions-154874852505.s3.eu-north-1.amazonaws.com/documents/b797f03bd896235afa1e932a2325d84c.jpg",
      "nb_tx_historique": 5.0,
      "comments": [
        {
          "date": "2026-06-22",
          "type": "COURIER",
          "content": "Date affichée : 2026-06-22 | Commune : Yopougon | Lieu : Yopougon a gauche carrefour centre social | Montant total : 364900 | Avance : 500000 | Frais transaction : 25000 | Frais retard : 39900 | Montant payé : 200000",
          "author": "evinne"
        },
        {
          "date": "2026-06-17",
          "type": "GENERIC_COMMENT",
          "content": "Appel (Sortant) : il est tombe brusquement malade et ses gérants ont fait n'importe quoi a son dépôt donc il promet de régler sa dette entièrement avant lundi",
          "author": "KoneMasse"
        },
        {
          "date": "2026-06-17",
          "type": "COURIER",
          "content": "Date affichée : 2026-06-17 | Commune : Yopougon | Lieu : Yopougon a gauche carrefour centre social | Montant total : 364900 | Avance : 500000 | Frais transaction : 25000 | Frais retard : 39900 | Montant payé : 200000",
          "author": "KoneMasse"
        },
        {
          "date": "2026-06-08",
          "type": "GENERIC_COMMENT",
          "content": "Appel (Sortant) [Recouvrement] : je vais un versement de 50 k aujourdhui",
          "author": "evinne"
        },
        {
          "date": "2026-06-04",
          "type": "GENERIC_COMMENT",
          "content": "Appel (Sortant) [Recouvrement] : il dit quil a eu un cas de force majeur sa fille etait malade mais il fera de son mieux pour payer demain",
          "author": "evinne"
        },
        {
          "date": "2026-06-02",
          "type": "GENERIC_COMMENT",
          "content": "Appel (Sortant) [Recouvrement] : aucune reponse",
          "author": "KoneMasse"
        }
      ]
    },
    {
      "tx_id": 19539.0,
      "merchant_id": 1928.0,
      "merchant_name": "ADOUKO ASSOHOUN APPOLINAIRE",
      "district": null,
      "phone": "+2250707983993",
      "supplier_name": "Distribution Bon prix Abobo",
      "montant": 133450.0,
      "date_achat": "2026-05-27",
      "maturity_date": "2026-06-03",
      "jours_retard": 21.0,
      "statut": "PENDING",
      "montant_paye": 90000.0,
      "montant_restant": 43450.0,
      "latitude": 5.4383331,
      "longitude": -4.0196637,
      "photo_url": null,
      "nb_tx_historique": 23.0,
      "comments": [
        {
          "date": "2026-06-22",
          "type": "COURIER",
          "content": "Date affichée : 2026-06-22 | Commune : Abobo | Lieu : Abobo Avenue Casa | Montant total : 55350 | Avance : 130000 | Frais transaction : 4500 | Frais retard : 10850 | Montant payé : 90000",
          "author": "evinne"
        },
        {
          "date": "2026-06-15",
          "type": "COURIER",
          "content": "Date affichée : 2026-06-15 | Commune : Abobo | Lieu : Abobo Avenue Casa | Montant total : 73950 | Avance : 130000 | Frais transaction : 4500 | Frais retard : 9450 | Montant payé : 70000",
          "author": "evinne"
        },
        {
          "date": "2026-06-11",
          "type": "GENERIC_COMMENT",
          "content": "Appel (Sortant) [Recouvrement] : je suis dans la circulation on se rappelle dans 25 mins",
          "author": "evinne"
        },
        {
          "date": "2026-06-05",
          "type": "GENERIC_COMMENT",
          "content": "Appel (Sortant) [Recouvrement] : il va payer le moite et dans deux trois jours il va solder",
          "author": "evinne"
        },
        {
          "date": "2026-06-05",
          "type": "GENERIC_COMMENT",
          "content": "Appel (Sortant) [Recouvrement] : aucune reponnse",
          "author": "evinne"
        },
        {
          "date": "2026-06-04",
          "type": "GENERIC_COMMENT",
          "content": "Appel (Sortant) [Recouvrement] : aucune reponse",
          "author": "evinne"
        }
      ]
    },
    {
      "tx_id": 19598.0,
      "merchant_id": 2063.0,
      "merchant_name": "KOFFI EUGENIE",
      "district": null,
      "phone": "+2250777544657",
      "supplier_name": "Distribution Bon prix Abobo",
      "montant": 170000.0,
      "date_achat": "2026-05-28",
      "maturity_date": "2026-06-04",
      "jours_retard": 20.0,
      "statut": "PENDING",
      "montant_paye": 100000.0,
      "montant_restant": 70000.0,
      "latitude": 5.4535062,
      "longitude": -4.0093729,
      "photo_url": null,
      "nb_tx_historique": 14.0,
      "comments": [
        {
          "date": "2026-06-22",
          "type": "COURIER",
          "content": "Date affichée : 2026-06-22 | Commune : Abobo | Lieu : Abobo Akeikoi | Montant total : 95600 | Avance : 170000 | Frais transaction : 6000 | Frais retard : 19600 | Montant payé : 100000",
          "author": "evinne"
        },
        {
          "date": "2026-06-15",
          "type": "COURIER",
          "content": "Date affichée : 2026-06-15 | Commune : Abobo | Lieu : Abobo Akeikoi | Montant total : 191400 | Avance : 170000 | Frais transaction : 6000 | Frais retard : 15400 | Montant payé : 0",
          "author": "evinne"
        },
        {
          "date": "2026-06-15",
          "type": "COURIER",
          "content": "Date affichée : 2026-06-15 | Commune : Abobo | Lieu : Abobo Akeikoi | Montant total : 191400 | Avance : 170000 | Frais transaction : 6000 | Frais retard : 15400 | Montant payé : 0",
          "author": "evinne"
        },
        {
          "date": "2026-06-11",
          "type": "GENERIC_COMMENT",
          "content": "Appel (Sortant) [Recouvrement] : aucune reponse",
          "author": "evinne"
        },
        {
          "date": "2026-06-09",
          "type": "GENERIC_COMMENT",
          "content": "Appel (Sortant) [Recouvrement] : aucune reponse",
          "author": "evinne"
        },
        {
          "date": "2026-06-08",
          "type": "GENERIC_COMMENT",
          "content": "Appel (Sortant) [Recouvrement] : aucune reponse",
          "author": "evinne"
        },
        {
          "date": "2026-06-05",
          "type": "GENERIC_COMMENT",
          "content": "Appel (Sortant) [Recouvrement] : elle va faire aujourhui",
          "author": "evinne"
        }
      ]
    },
    {
      "tx_id": 19632.0,
      "merchant_id": 2445.0,
      "merchant_name": "KOHIRIME SOKO LEA",
      "district": "Adjamé",
      "phone": "+2250747665988",
      "supplier_name": "Sd Gonty Adjamé - liberté ",
      "montant": 114050.0,
      "date_achat": "2026-05-29",
      "maturity_date": "2026-06-05",
      "jours_retard": 19.0,
      "statut": "PENDING",
      "montant_paye": 56000.0,
      "montant_restant": 58050.0,
      "latitude": 5.3682569,
      "longitude": -4.026649,
      "photo_url": "https://fineract-waribei-transactions-154874852505.s3.eu-north-1.amazonaws.com/documents/2440df4c02841bc8da7dc40d40eee302.jpg",
      "nb_tx_historique": 7.0,
      "comments": [
        {
          "date": "2026-06-24",
          "type": "LETTER_GIVEN_TO_AGENT",
          "content": "RECOUVREMENT : LETTER_GIVEN_TO_AGENT : Visite : Elle a effectué un versement de 26.000 puis a promis de payer 15.000 le soir même et solder le vendredi",
          "author": "alassane"
        },
        {
          "date": "2026-06-22",
          "type": "GENERIC_COMMENT",
          "content": "Appel (Sortant) [Recouvrement] : Injoignable",
          "author": "KoneMasse"
        },
        {
          "date": "2026-06-22",
          "type": "COURIER",
          "content": "Date affichée : 2026-06-22 | Commune : Adjamé | Lieu : CRS portail fermé | Montant total : 57900 | Avance : 80000 | Frais transaction : 3000 | Frais retard : 4900 | Montant payé : 30000",
          "author": "evinne"
        },
        {
          "date": "2026-06-15",
          "type": "COURIER",
          "content": "Date affichée : 2026-06-15 | Commune : Adjamé | Lieu : CRS portail fermé | Montant total : 56500 | Avance : 80000 | Frais transaction : 3000 | Frais retard : 3500 | Montant payé : 30000",
          "author": "evinne"
        },
        {
          "date": "2026-06-15",
          "type": "COURIER",
          "content": "Date affichée : 2026-06-15 | Commune : Adjamé | Lieu : CRS portail fermé | Montant total : 56500 | Avance : 80000 | Frais transaction : 3000 | Frais retard : 3500 | Montant payé : 30000",
          "author": "evinne"
        },
        {
          "date": "2026-06-11",
          "type": "GENERIC_COMMENT",
          "content": "Appel (Sortant) [Recouvrement] : elle va faire le necessiare ce soir au demain matin",
          "author": "evinne"
        },
        {
          "date": "2026-06-09",
          "type": "GENERIC_COMMENT",
          "content": "Appel (Sortant) [Recouvrement] : je vais faire un versement aujourdhui",
          "author": "evinne"
        }
      ]
    },
    {
      "tx_id": 19732.0,
      "merchant_id": 2494.0,
      "merchant_name": "ALLANGBA ORIANNE CHARLY",
      "district": "Yopougon",
      "phone": "+2250759736200",
      "supplier_name": "Timo distribution Agbayaté",
      "montant": 80000.0,
      "date_achat": "2026-05-30",
      "maturity_date": "2026-06-06",
      "jours_retard": 18.0,
      "statut": "PENDING",
      "montant_paye": 30000.0,
      "montant_restant": 50000.0,
      "latitude": 5.3186414,
      "longitude": -4.0478408,
      "photo_url": "https://fineract-waribei-transactions-154874852505.s3.eu-north-1.amazonaws.com/documents/acaa56b5985a232c0981d74f9c53119a.jpg",
      "nb_tx_historique": 5.0,
      "comments": [
        {
          "date": "2026-06-22",
          "type": "COURIER",
          "content": "Date affichée : 2026-06-22 | Commune : Yopougon | Lieu : Agbayaté | Montant total : 59300 | Avance : 80000 | Frais transaction : 3000 | Frais retard : 6300 | Montant payé : 30000",
          "author": "evinne"
        },
        {
          "date": "2026-06-15",
          "type": "COURIER",
          "content": "Date affichée : 2026-06-15 | Commune : Yopougon | Lieu : Agbayaté | Montant total : 57550 | Avance : 80000 | Frais transaction : 3000 | Frais retard : 4550 | Montant payé : 30000",
          "author": "evinne"
        },
        {
          "date": "2026-06-09",
          "type": "GENERIC_COMMENT",
          "content": "Appel (Sortant) [Recouvrement] : aucune reponse",
          "author": "evinne"
        }
      ]
    },
    {
      "tx_id": 19741.0,
      "merchant_id": 1123.0,
      "merchant_name": "DOUBY BI TAH AURELIEN",
      "district": null,
      "phone": "+2250707949442",
      "supplier_name": "Dépôt la source Koumassi ",
      "montant": 100000.0,
      "date_achat": "2026-05-31",
      "maturity_date": "2026-06-07",
      "jours_retard": 17.0,
      "statut": "PENDING",
      "montant_paye": 0.0,
      "montant_restant": 100000.0,
      "latitude": 5.2997296,
      "longitude": -3.969406,
      "photo_url": null,
      "nb_tx_historique": 51.0,
      "comments": [
        {
          "date": "2026-06-22",
          "type": "COURIER",
          "content": "Date affichée : 2026-06-22 | Commune : Koumassi | Lieu : Koumassi campement, virage | Montant total : 112800 | Avance : 100000 | Frais transaction : 3000 | Frais retard : 9800 | Montant payé : 0",
          "author": "evinne"
        },
        {
          "date": "2026-06-15",
          "type": "COURIER",
          "content": "Date affichée : 2026-06-15 | Commune : Koumassi | Lieu : Koumassi campement, virage | Montant total : 108600 | Avance : 100000 | Frais transaction : 3000 | Frais retard : 5600 | Montant payé : 0",
          "author": "evinne"
        },
        {
          "date": "2026-06-09",
          "type": "GENERIC_COMMENT",
          "content": "Appel (Sortant) [Recouvrement] : ligne occupée",
          "author": "evinne"
        }
      ]
    },
    {
      "tx_id": 19764.0,
      "merchant_id": 523.0,
      "merchant_name": "Zikida Armelle edith Dasse",
      "district": null,
      "phone": "+2250748467998",
      "supplier_name": "Centrale dépôt",
      "montant": 74250.0,
      "date_achat": "2026-05-31",
      "maturity_date": "2026-06-07",
      "jours_retard": 17.0,
      "statut": "PENDING",
      "montant_paye": 0.0,
      "montant_restant": 74250.0,
      "latitude": null,
      "longitude": null,
      "photo_url": null,
      "nb_tx_historique": 6.0,
      "comments": [
        {
          "date": "2026-06-22",
          "type": "COURIER",
          "content": "Date affichée : 2026-06-22 | Montant total : 56400 | Avance : 50000 | Frais transaction : 1500 | Frais retard : 4900 | Montant payé : 0",
          "author": "evinne"
        },
        {
          "date": "2026-06-18",
          "type": "LETTER_GIVEN_TO_AGENT",
          "content": "RECOUVREMENT : LETTER_GIVEN_TO_AGENT : Appel : La cliente signifie faire un versement de 20mill demain",
          "author": "francisAka"
        },
        {
          "date": "2026-06-15",
          "type": "COURIER",
          "content": "Date affichée : 2026-06-15 | Montant total : 54300 | Avance : 50000 | Frais transaction : 1500 | Frais retard : 2800 | Montant payé : 0",
          "author": "evinne"
        },
        {
          "date": "2026-06-09",
          "type": "GENERIC_COMMENT",
          "content": "Appel (Sortant) [Recouvrement] : aucune reponse",
          "author": "evinne"
        }
      ]
    },
    {
      "tx_id": 19768.0,
      "merchant_id": 1139.0,
      "merchant_name": "DAINGUI EUNICE FENICIA",
      "district": null,
      "phone": "+2250709690697",
      "supplier_name": "Sd el shaada ",
      "montant": 150000.0,
      "date_achat": "2026-06-01",
      "maturity_date": "2026-06-08",
      "jours_retard": 16.0,
      "statut": "PENDING",
      "montant_paye": 100000.0,
      "montant_restant": 50000.0,
      "latitude": 5.3036478,
      "longitude": -3.9555593,
      "photo_url": null,
      "nb_tx_historique": 22.0,
      "comments": [
        {
          "date": "2026-06-22",
          "type": "COURIER",
          "content": "Date affichée : 2026-06-22 | Commune : Koumassi | Lieu : Koumassi 05 | Montant total : 69200 | Avance : 150000 | Frais transaction : 4500 | Frais retard : 14700 | Montant payé : 100000",
          "author": "evinne"
        },
        {
          "date": "2026-06-18",
          "type": "LETTER_GIVEN_TO_AGENT",
          "content": "RECOUVREMENT : LETTER_GIVEN_TO_AGENT : Appel : Cliente signifie solder dimanche vu qu'elle a eu un avc",
          "author": "francisAka"
        },
        {
          "date": "2026-06-15",
          "type": "COURIER",
          "content": "Date affichée : 2026-06-15 | Commune : Koumassi | Lieu : Koumassi 05 | Montant total : 161850 | Avance : 150000 | Frais transaction : 4500 | Frais retard : 7350 | Montant payé : 0",
          "author": "evinne"
        },
        {
          "date": "2026-06-09",
          "type": "GENERIC_COMMENT",
          "content": "Appel (Sortant) [Recouvrement] : elle dit qu elle est a l hopital et quelle va faire quand elle sera prete  elle  fera signe  a miss koné",
          "author": "evinne"
        }
      ]
    },
    {
      "tx_id": 19785.0,
      "merchant_id": 2371.0,
      "merchant_name": "GANSAGNE MAHAMOUDOU",
      "district": "Abobo",
      "phone": "+2250708178003",
      "supplier_name": "SD Diviry",
      "montant": 100000.0,
      "date_achat": "2026-06-01",
      "maturity_date": "2026-06-08",
      "jours_retard": 16.0,
      "statut": "PENDING",
      "montant_paye": 0.0,
      "montant_restant": 100000.0,
      "latitude": 5.3784531,
      "longitude": -3.9995519,
      "photo_url": "https://fineract-waribei-transactions-154874852505.s3.eu-north-1.amazonaws.com/documents/42525d2783c474f15a05455d4f46c5ea.jpg",
      "nb_tx_historique": 11.0,
      "comments": [
        {
          "date": "2026-06-22",
          "type": "COURIER",
          "content": "Date affichée : 2026-06-22 | Commune : Abobo | Lieu : Abobote près de l’hôtel Grand maximum | Montant total : 92800 | Avance : 80000 | Frais transaction : 3000 | Frais retard : 9800 | Montant payé : 0",
          "author": "evinne"
        },
        {
          "date": "2026-06-15",
          "type": "COURIER",
          "content": "Date affichée : 2026-06-15 | Commune : Abobo | Lieu : Abobote près de l’hôtel Grand maximum | Montant total : 87900 | Avance : 80000 | Frais transaction : 3000 | Frais retard : 4900 | Montant payé : 0",
          "author": "evinne"
        },
        {
          "date": "2026-06-10",
          "type": "GENERIC_COMMENT",
          "content": "Appel (Sortant) [Recouvrement] : Injoignable",
          "author": "evinne"
        },
        {
          "date": "2026-06-09",
          "type": "GENERIC_COMMENT",
          "content": "Appel (Sortant) [Recouvrement] : auucne reponse",
          "author": "evinne"
        }
      ]
    },
    {
      "tx_id": 19853.0,
      "merchant_id": 1414.0,
      "merchant_name": "KIPRE MARIE LUCIE",
      "district": null,
      "phone": "+2250749822589",
      "supplier_name": "Sd yssouf Soweto",
      "montant": 62850.0,
      "date_achat": "2026-06-02",
      "maturity_date": "2026-06-09",
      "jours_retard": 15.0,
      "statut": "PENDING",
      "montant_paye": 0.0,
      "montant_restant": 62850.0,
      "latitude": 5.2978252,
      "longitude": -3.9759198,
      "photo_url": null,
      "nb_tx_historique": 16.0,
      "comments": [
        {
          "date": "2026-06-22",
          "type": "COURIER",
          "content": "Date affichée : 2026-06-22 | Commune : Marcory | Lieu : Marcory sicogi parking blonty | Montant total : 74950 | Avance : 62850 | Frais transaction : 3000 | Frais retard : 9100 | Montant payé : 0",
          "author": "evinne"
        },
        {
          "date": "2026-06-10",
          "type": "GENERIC_COMMENT",
          "content": "Appel (Sortant) [Recouvrement] : eeeeh waribei pardon ohhhh jai oublie probleme est trop bon si cest pas ce soir ca sera demain encore desole",
          "author": "evinne"
        },
        {
          "date": "2026-06-10",
          "type": "GENERIC_COMMENT",
          "content": "Appel:10-06-2026:18-18:00:30:Allo? Oui? Bonsoir M. Kwasi. Bonsoir M. Kwasi. C'est Waribe. Euh oui. M. je vais vous appeler pour... Oh j'ai bougé un peu deux jours là. Où je suis? Euh... je rentre... comment on appelle? Demain. D'accord. Euh... je rentre demain. C'est pourquoi je n'ai pas... je n'ai pas pu faire. Je rentre demain. J'ai voulu même vous appeler même pour lui de m'excuser quoi. D'accord. Alors vous rentrez demain. Euh... voilà je rentre demain. Si je veux. Ouais. Pas de souci. Ok. Mais la pénalité va se rajouter encore. Y'a pas de problème moi. Y'a pas de problème. Mais je suis sûr que vous m'en foutez. D'accord M. donc à demain. Euh... je suis sûr que vous m'en foutez.:Recouvrement",
          "author": "evinne"
        }
      ]
    },
    {
      "tx_id": 19937.0,
      "merchant_id": 2723.0,
      "merchant_name": "Karim Ouattara",
      "district": "Yopougon",
      "phone": "2250709150004",
      "supplier_name": "NCDI.S ",
      "montant": 165700.0,
      "date_achat": "2026-06-03",
      "maturity_date": "2026-06-10",
      "jours_retard": 14.0,
      "statut": "PENDING",
      "montant_paye": 55000.0,
      "montant_restant": 110700.0,
      "latitude": 5.3141808,
      "longitude": -4.0850159,
      "photo_url": "https://fineract-waribei-transactions-154874852505.s3.eu-north-1.amazonaws.com/documents/85841b44734662d80dd7f17970b611b6.jpg",
      "nb_tx_historique": 2.0,
      "comments": [
        {
          "date": "2026-06-22",
          "type": "COURIER",
          "content": "Date affichée : 2026-06-22 | Commune : Yopougon | Lieu : Azito quartier laurier | Montant total : 98950 | Avance : 140000 | Frais transaction : 4500 | Frais retard : 9450 | Montant payé : 55000",
          "author": "evinne"
        },
        {
          "date": "2026-06-11",
          "type": "GENERIC_COMMENT",
          "content": "Appel (Sortant) : il rentre comme ca sur abidjan car il etait en deplacement .il fera son paiement ce soir",
          "author": "KoneMasse"
        }
      ]
    },
    {
      "tx_id": 19927.0,
      "merchant_id": 1847.0,
      "merchant_name": "DASSOUNDIAL GAYE SAIDOU FRANCIS",
      "district": null,
      "phone": "+2250101499335",
      "supplier_name": "Sd WiFi Gonzague",
      "montant": 100000.0,
      "date_achat": "2026-06-03",
      "maturity_date": "2026-06-10",
      "jours_retard": 14.0,
      "statut": "PENDING",
      "montant_paye": 88700.0,
      "montant_restant": 11300.0,
      "latitude": 5.2474986,
      "longitude": -3.9188698,
      "photo_url": null,
      "nb_tx_historique": 23.0,
      "comments": [
        {
          "date": "2026-06-22",
          "type": "COURIER",
          "content": "Date affichée : 2026-06-22 | Commune : Port-Bouët | Lieu : Port Bouet quartier Adjoufou boutique Olo | Montant total : 18850 | Avance : 100000 | Frais transaction : 3000 | Frais retard : 4550 | Montant payé : 88700",
          "author": "evinne"
        },
        {
          "date": "2026-06-11",
          "type": "GENERIC_COMMENT",
          "content": "Appel (Sortant) : il a fait un paiement partiel aujourd'hui ,il fera le reste demain",
          "author": "KoneMasse"
        }
      ]
    },
    {
      "tx_id": 19890.0,
      "merchant_id": 2368.0,
      "merchant_name": "ETIEN KOUAKOU ETIENNE",
      "district": "Yopougon",
      "phone": "+2250708037090",
      "supplier_name": "La pieuvre ",
      "montant": 80349.0,
      "date_achat": "2026-06-03",
      "maturity_date": "2026-06-10",
      "jours_retard": 14.0,
      "statut": "PENDING",
      "montant_paye": 0.0,
      "montant_restant": 80349.0,
      "latitude": 5.3196798,
      "longitude": -4.1008379,
      "photo_url": "https://fineract-waribei-transactions-154874852505.s3.eu-north-1.amazonaws.com/documents/bf942b9c72ae2de981f718a177b9a286.jpg",
      "nb_tx_historique": 6.0,
      "comments": [
        {
          "date": "2026-06-22",
          "type": "COURIER",
          "content": "Date affichée : 2026-06-22 | Commune : Yopougon | Lieu : Yopougon carrefour lokoua CIE | Montant total : 91400 | Avance : 80000 | Frais transaction : 3000 | Frais retard : 8400 | Montant payé : 0",
          "author": "evinne"
        },
        {
          "date": "2026-06-11",
          "type": "GENERIC_COMMENT",
          "content": "Appel (Sortant) : il raccroche mes appels et me laisse un message disant qu'il est occupée et qu'il me rappelle",
          "author": "KoneMasse"
        }
      ]
    },
    {
      "tx_id": 20215.0,
      "merchant_id": 2617.0,
      "merchant_name": "GBEULY GUIHOUNOU GUY ARMAND",
      "district": "Cocody",
      "phone": "2250757096137",
      "supplier_name": "Sd Guitty bingerville",
      "montant": 67300.0,
      "date_achat": "2026-06-04",
      "maturity_date": "2026-06-11",
      "jours_retard": 13.0,
      "statut": "PENDING",
      "montant_paye": 0.0,
      "montant_restant": 67300.0,
      "latitude": 5.3742716,
      "longitude": -3.9270721,
      "photo_url": "https://fineract-waribei-transactions-154874852505.s3.eu-north-1.amazonaws.com/documents/216a39ad48ea052470163eefcd59e954.jpg",
      "nb_tx_historique": 4.0,
      "comments": [
        {
          "date": "2026-06-22",
          "type": "COURIER",
          "content": "Date affichée : 2026-06-22 | Commune : Cocody | Lieu : Cocody palmeraie ephrata | Montant total : 78000 | Avance : 67300 | Frais transaction : 3000 | Frais retard : 7700 | Montant payé : 0",
          "author": "evinne"
        },
        {
          "date": "2026-06-12",
          "type": "GENERIC_COMMENT",
          "content": "Appel (Sortant) [Recouvrement] : il verifie sa date et il nous revient",
          "author": "evinne"
        },
        {
          "date": "2026-06-08",
          "type": "GENERIC_COMMENT",
          "content": "Appel (Sortant) [Confirmation] : aucune reponse",
          "author": "evinne"
        }
      ]
    },
    {
      "tx_id": 19996.0,
      "merchant_id": 2823.0,
      "merchant_name": "augustin Zougrana",
      "district": "Abobo",
      "phone": "2250584554289",
      "supplier_name": "Fk distribution abobo",
      "montant": 137400.0,
      "date_achat": "2026-06-05",
      "maturity_date": "2026-06-12",
      "jours_retard": 12.0,
      "statut": "PENDING",
      "montant_paye": 0.0,
      "montant_restant": 137400.0,
      "latitude": 5.4305424,
      "longitude": -3.9876565,
      "photo_url": "https://fineract-waribei-transactions-154874852505.s3.eu-north-1.amazonaws.com/documents/b461d10621dffdf1c837da4ae48f3b2c.jpg",
      "nb_tx_historique": 1.0,
      "comments": [
        {
          "date": "2026-06-22",
          "type": "COURIER",
          "content": "Date affichée : 2026-06-22 | Commune : Abobo | Lieu : Abobo 4 croix carrefour salvador | Montant total : 110000 | Avance : 100000 | Frais transaction : 3000 | Frais retard : 7000 | Montant payé : 0",
          "author": "evinne"
        },
        {
          "date": "2026-06-19",
          "type": "GENERIC_COMMENT",
          "content": "Appel (Sortant) [Recouvrement] : Injoignable",
          "author": "evinne"
        }
      ]
    },
    {
      "tx_id": 19607.0,
      "merchant_id": 1852.0,
      "merchant_name": "ZAPO FLAVIE",
      "district": null,
      "phone": "+2250565241626",
      "supplier_name": "Socob Locodjro",
      "montant": 400000.0,
      "date_achat": "2026-05-30",
      "maturity_date": "2026-06-13",
      "jours_retard": 11.0,
      "statut": "PENDING",
      "montant_paye": 0.0,
      "montant_restant": 400000.0,
      "latitude": 5.3411763,
      "longitude": -4.1553737,
      "photo_url": null,
      "nb_tx_historique": 14.0,
      "comments": [
        {
          "date": "2026-06-23",
          "type": "GENERIC_COMMENT",
          "content": "Appel (Sortant) [Recouvrement] : Injoignable",
          "author": "KoneMasse"
        },
        {
          "date": "2026-06-23",
          "type": "COURIER",
          "content": "Date affichée : 2026-06-23 | Commune : Yopougon | Lieu : Yopougon terminus 40 | Montant total : 448000 | Avance : 400000 | Frais transaction : 20000 | Frais retard : 28000 | Montant payé : 0",
          "author": "KoneMasse"
        },
        {
          "date": "2026-06-19",
          "type": "GENERIC_COMMENT",
          "content": "Appel (Sortant) [Recouvrement] : cliente indisponible",
          "author": "evinne"
        },
        {
          "date": "2026-06-17",
          "type": "GENERIC_COMMENT",
          "content": "Appel (Sortant) [Recouvrement] : Injoignable",
          "author": "evinne"
        },
        {
          "date": "2026-06-17",
          "type": "GENERIC_COMMENT",
          "content": "Appel (Entrant) : aucune reponse",
          "author": "KoneMasse"
        }
      ]
    },
    {
      "tx_id": 20110.0,
      "merchant_id": 2606.0,
      "merchant_name": "TIZIE LOU NENENAN ALBERTINE",
      "district": "Port-Bouët",
      "phone": "2250788505184",
      "supplier_name": "Sd TDS PORT BOUET ",
      "montant": 239800.0,
      "date_achat": "2026-06-06",
      "maturity_date": "2026-06-13",
      "jours_retard": 11.0,
      "statut": "PENDING",
      "montant_paye": 90000.0,
      "montant_restant": 149800.0,
      "latitude": 5.239640143786549,
      "longitude": -3.889686898917204,
      "photo_url": "https://fineract-waribei-transactions-154874852505.s3.eu-north-1.amazonaws.com/documents/52bf5ac6ebf552724945434e12f0b13f.jpg",
      "nb_tx_historique": 5.0,
      "comments": [
        {
          "date": "2026-06-22",
          "type": "COURIER",
          "content": "Date affichée : 2026-06-22 | Commune : Port-Bouët | Lieu : Gonzague carrefour dieudonné | Montant total : 104750 | Avance : 180000 | Frais transaction : 6000 | Frais retard : 8750 | Montant payé : 90000",
          "author": "evinne"
        },
        {
          "date": "2026-06-19",
          "type": "GENERIC_COMMENT",
          "content": "Appel (Sortant) [Recouvrement] : comme ya probleme de boisson la moi jai pris l argent la pour travailler",
          "author": "evinne"
        },
        {
          "date": "2026-06-17",
          "type": "GENERIC_COMMENT",
          "content": "Appel (Sortant) [Recouvrement] : cest compris demain je vais faire",
          "author": "evinne"
        }
      ]
    },
    {
      "tx_id": 20102.0,
      "merchant_id": 2364.0,
      "merchant_name": "BROU PIEKA ANNIE MARLENE",
      "district": "Cocody",
      "phone": "+2250707095530",
      "supplier_name": "Dépôt Redis angré",
      "montant": 135000.0,
      "date_achat": "2026-06-06",
      "maturity_date": "2026-06-13",
      "jours_retard": 11.0,
      "statut": "PENDING",
      "montant_paye": 0.0,
      "montant_restant": 135000.0,
      "latitude": 5.395776238863882,
      "longitude": -3.940689261433941,
      "photo_url": "https://fineract-waribei-transactions-154874852505.s3.eu-north-1.amazonaws.com/documents/fd30f3b25b0c7880631e6b913921d111.jpg",
      "nb_tx_historique": 15.0,
      "comments": [
        {
          "date": "2026-06-22",
          "type": "COURIER",
          "content": "Date affichée : 2026-06-22 | Commune : Cocody | Lieu : Djorobite 1 | Montant total : 109300 | Avance : 100000 | Frais transaction : 3000 | Frais retard : 6300 | Montant payé : 0",
          "author": "evinne"
        },
        {
          "date": "2026-06-19",
          "type": "GENERIC_COMMENT",
          "content": "Appel (Sortant) [Recouvrement] : Injoignable",
          "author": "evinne"
        },
        {
          "date": "2026-06-17",
          "type": "GENERIC_COMMENT",
          "content": "Appel (Sortant) [Recouvrement] : ligne occupéé",
          "author": "evinne"
        }
      ]
    },
    {
      "tx_id": 19738.0,
      "merchant_id": 1779.0,
      "merchant_name": "KOULAI ALEX-PACOME",
      "district": null,
      "phone": "+2250707340205",
      "supplier_name": "Sd sportif ",
      "montant": 828500.0,
      "date_achat": "2026-05-31",
      "maturity_date": "2026-06-14",
      "jours_retard": 10.0,
      "statut": "PENDING",
      "montant_paye": 0.0,
      "montant_restant": 828500.0,
      "latitude": 5.3748083,
      "longitude": -4.0907898,
      "photo_url": null,
      "nb_tx_historique": 22.0,
      "comments": [
        {
          "date": "2026-06-23",
          "type": "COURIER",
          "content": "Date affichée : 2026-06-23 | Commune : Port-Bouët | Lieu : Port Bouet Gonzague carrefour ONG | Montant total : 556500 | Avance : 500000 | Frais transaction : 25000 | Frais retard : 31500 | Montant payé : 0",
          "author": "KoneMasse"
        },
        {
          "date": "2026-06-22",
          "type": "GENERIC_COMMENT",
          "content": "Appel (Sortant) [Recouvrement] : aucune reponse",
          "author": "evinne"
        },
        {
          "date": "2026-06-22",
          "type": "COURIER",
          "content": "Date affichée : 2026-06-22 | Commune : Port-Bouët | Lieu : Port Bouet Gonzague carrefour ONG | Montant total : 553000 | Avance : 500000 | Frais transaction : 25000 | Frais retard : 28000 | Montant payé : 0",
          "author": "evinne"
        },
        {
          "date": "2026-06-22",
          "type": "COURIER",
          "content": "Date affichée : 2026-06-22 | Commune : Port-Bouët | Lieu : Port Bouet Gonzague carrefour ONG | Montant total : 553000 | Avance : 500000 | Frais transaction : 25000 | Frais retard : 28000 | Montant payé : 0",
          "author": "evinne"
        },
        {
          "date": "2026-06-22",
          "type": "COURIER",
          "content": "Date affichée : 2026-06-22 | Commune : Port-Bouët | Lieu : Port Bouet Gonzague carrefour ONG | Montant total : 553000 | Avance : 500000 | Frais transaction : 25000 | Frais retard : 28000 | Montant payé : 0",
          "author": "evinne"
        },
        {
          "date": "2026-06-19",
          "type": "GENERIC_COMMENT",
          "content": "Appel (Sortant) [Recouvrement] : il va faire un versement aujourdhui",
          "author": "evinne"
        },
        {
          "date": "2026-06-18",
          "type": "GENERIC_COMMENT",
          "content": "Appel (Sortant) [Recouvrement] : aucune reponse",
          "author": "evinne"
        },
        {
          "date": "2026-06-17",
          "type": "GENERIC_COMMENT",
          "content": "Appel (Sortant) [Recouvrement] : aucune reponse",
          "author": "evinne"
        }
      ]
    },
    {
      "tx_id": 20193.0,
      "merchant_id": 289.0,
      "merchant_name": "Akouba Jeanne marie Kouman",
      "district": null,
      "phone": "+2250545873061",
      "supplier_name": "Stephy service distribution Marcory ",
      "montant": 539500.0,
      "date_achat": "2026-06-08",
      "maturity_date": "2026-06-15",
      "jours_retard": 9.0,
      "statut": "PENDING",
      "montant_paye": 305000.0,
      "montant_restant": 234500.0,
      "latitude": 5.3076868,
      "longitude": -3.9498955,
      "photo_url": null,
      "nb_tx_historique": 11.0,
      "comments": [
        {
          "date": "2026-06-22",
          "type": "GENERIC_COMMENT",
          "content": "Appel (Sortant) [Recouvrement] : aucune reponse",
          "author": "evinne"
        },
        {
          "date": "2026-06-19",
          "type": "GENERIC_COMMENT",
          "content": "Appel (Sortant) [Recouvrement] : je vais faire un versement",
          "author": "evinne"
        },
        {
          "date": "2026-06-17",
          "type": "GENERIC_COMMENT",
          "content": "Appel (Sortant) [Recouvrement] : demain ou apres demain",
          "author": "evinne"
        },
        {
          "date": "2026-06-08",
          "type": "GENERIC_COMMENT",
          "content": "Appel:08-06-2026:14-03:00:05:Allô ? Allô, bonjour. Bonjour monsieur. Madame Agua, Sandrine, comment allez-vous ? Ça va bien. C'est Monsieur Touré de Ouaribé. Oui. C'est quoi le souci avec le paiement ? C'est quoi le souci avec le paiement ? Oui. Je ne comprends pas votre question. Oui, parce que vous connaissez Monsieur Touré bien. Monsieur Touré, oui. D'accord. Et on a établi un échéancier que vous devriez respecter. D'accord. La dernière fois je vous ai même envoyé le lien du paiement via WhatsApp et depuis lors vous n'avez pas réagi. Oui. Donc c'est pourquoi je vous demande c'est quoi le souci avec le paiement. D'accord. D'accord, Madame Sandrine. Madame Sandrine. Oui. J'ai été beaucoup compréhensif sur cette situation. Vous savez ça. Oui. Et hier j'étais dans votre espace. J'ai vu, il y avait de la clientèle, ça consommait de l'argent. Hier c'est moi-même qui étais là-bas. Hier c'est moi-même qui étais là-bas. Vous n'avez pas dit que je suis passé le dimanche, le samedi, pardon. Je suis passé plutôt le samedi. Samedi. Oui. Non, on ne m'a rien dit. D'accord. D'accord. Le samedi, je suis allé faire les premiers, manquer, manquer, manquer. Non, non. La journée d'hier, à treize, moi je suis allé là-bas pour aller voir. D'accord. La boisson que j'ai mis là-bas, l'argent qui doit ressortir, le capital qui doit ressortir n'est pas ressorti et puis on me dit qu'il manque encore. Ok, je vais. Il faut respecter l'échéancier qu'on établit. Je vais vous envoyer le lien, il faut faire le paiement. Et à partir d'aujourd'hui là, il faut solder, il ne reste plus assez. Mais aujourd'hui là, je suis en train de vous expliquer un truc. Je dis aujourd'hui, moi je ne refuse pas de payer. Mais vous aussi comprenez, aujourd'hui là, je n'ai pas l'argent. Je veux que vous compreniez une chose. Non, je suis en train de vous expliquer. Non, non, écoutez-moi. Je n'ai pas refusé de payer. Ecoutez-moi. Moi je ne dois pas. Je n'ai jamais pris l'arbre de Waribe et puis vous dites que je ne vais pas payer. Je vous ai toujours payé. Il y a une situation qui est arrivée. Et puis je lui ai dit que je vais payer 10 000 par semaine. Mais il y a un truc qui est arrivé. C'est en train de chercher l'argent pour vous payer. Je n'ai jamais dit que je ne paye pas. Moi, mes vêtements, mes bébés. Votre échéancier de paiement, vous ne l'avez pas fait. Oui. C'est ça. Je n'ai jamais dit que je ne paye pas. Vous ne pouvez pas me dire que vous allez m'envoyer un lien aujourd'hui. Mais il y a la clientèle. Encore des boissons, 5 500, ils ont payé. Boissons qui étaient près de 30 000, ils ont fait manquer. Et puis il y a 5 500. Madame, je n'ai pas refusé de payer. On va vous envoyer le lien. Si le paiement n'est pas faible, la prochaine fois que je vais arriver là-bas, ce ne sera plus pour établir l'échéancier ni pour négocier. Donc, je vais poser une action. Mais quand tu parles comme ça, tu parles comme ça à ta clientèle. C'est comme ça. Une clientèle qui a eu des problèmes. Tu n'as jamais refusé de payer. La deuxième fois que je suis arrivé, ce n'est pas comme ça que j'ai parlé. Mais quand tu as... C'est parce que je n'ai pas reçu de votre engagement. Non, non. Ce n'est pas un non-reçu. Le lien qu'ils m'ont envoyé là. Le truc qu'ils m'ont envoyé là. Ils m'ont dit jusqu'au 14. Moi, je sentais que c'était là. Mais s'il n'a jamais reçu ça. Il vous a dit jusqu'au 14. Attends. Laisse-moi te parler d'abord. Ce n'est pas après le truc au 14. Quand tu m'envoies le lien, est-ce que je ne te paye pas? Quand tu m'envoies le lien, je ne te paye pas. Je vous envoie le lien, vous n'avez pas payé. C'est pourquoi je vous appelle. Non, non. Quand tu m'envoies le lien, est-ce que je ne te paye pas? Vous ne payez pas. Quand tu m'envoies le lien, je ne te paye pas. C'est ça, ils sont détestés. Il faut me comprendre aussi. Je ne peux pas vous comprendre. Je dis qu'ils sont détestés. Pourquoi il n'y a plus ça? Tu ne peux pas me comprendre. Je ne peux pas vous comprendre. Ça fait combien de mois maintenant pour une créance qui est censée durer une semaine? Mais une créance qui est censée durer une semaine. Est-ce que toi, tu arrives à me comprendre? Ils sont détestés. Je ne refuse pas de payer. Je le connais. Envoie-lui le lien de son paiement. Je n'ai pas refusé de payer. Aujourd'hui, je n'ai pas l'argent. Je dis qu'ils sont détestés. J'ai compris.:Verification transaction",
          "author": "evinne"
        }
      ]
    },
    {
      "tx_id": 19798.0,
      "merchant_id": 1860.0,
      "merchant_name": "YAPO API GWLADYS",
      "district": null,
      "phone": "+2250788465072",
      "supplier_name": "Socob Locodjro",
      "montant": 300000.0,
      "date_achat": "2026-06-01",
      "maturity_date": "2026-06-15",
      "jours_retard": 9.0,
      "statut": "PENDING",
      "montant_paye": 0.0,
      "montant_restant": 300000.0,
      "latitude": 5.3340551,
      "longitude": -4.093384,
      "photo_url": null,
      "nb_tx_historique": 14.0,
      "comments": [
        {
          "date": "2026-06-23",
          "type": "GENERIC_COMMENT",
          "content": "Appel (Sortant) [Recouvrement] : aucune reponse",
          "author": "KoneMasse"
        },
        {
          "date": "2026-06-23",
          "type": "COURIER",
          "content": "Date affichée : 2026-06-23 | Commune : Yopougon | Lieu : Yopougon 47 en face de l'école ciel pluriel | Montant total : 331800 | Avance : 300000 | Frais transaction : 15000 | Frais retard : 16800 | Montant payé : 0",
          "author": "KoneMasse"
        },
        {
          "date": "2026-06-23",
          "type": "COURIER",
          "content": "Date affichée : 2026-06-23 | Commune : Yopougon | Lieu : Yopougon 47 en face de l'école ciel pluriel | Montant total : 331800 | Avance : 300000 | Frais transaction : 15000 | Frais retard : 16800 | Montant payé : 0",
          "author": "KoneMasse"
        },
        {
          "date": "2026-06-22",
          "type": "GENERIC_COMMENT",
          "content": "Appel (Sortant) [Recouvrement] : aucune reponse",
          "author": "evinne"
        },
        {
          "date": "2026-06-22",
          "type": "COURIER",
          "content": "Date affichée : 2026-06-22 | Commune : Yopougon | Lieu : Yopougon 47 en face de l'école ciel pluriel | Montant total : 329700 | Avance : 300000 | Frais transaction : 15000 | Frais retard : 14700 | Montant payé : 0",
          "author": "evinne"
        },
        {
          "date": "2026-06-18",
          "type": "GENERIC_COMMENT",
          "content": "Appel (Sortant) [Recouvrement] : jusqu a samedi pour le remboursement",
          "author": "evinne"
        },
        {
          "date": "2026-06-18",
          "type": "GENERIC_COMMENT",
          "content": "Appel (Sortant) [Recouvrement] : aucune reponse",
          "author": "evinne"
        },
        {
          "date": "2026-06-17",
          "type": "GENERIC_COMMENT",
          "content": "Appel (Sortant) [Recouvrement] : aucune reponse",
          "author": "evinne"
        },
        {
          "date": "2026-06-17",
          "type": "GENERIC_COMMENT",
          "content": "Appel (Sortant) [Recouvrement] : aucune reponse",
          "author": "KoneMasse"
        }
      ]
    },
    {
      "tx_id": 20199.0,
      "merchant_id": 2537.0,
      "merchant_name": "YAO LOUKOU JACQUES",
      "district": "Koumassi",
      "phone": "2250504242852",
      "supplier_name": "Sd yssouf Soweto",
      "montant": 92350.0,
      "date_achat": "2026-06-08",
      "maturity_date": "2026-06-15",
      "jours_retard": 9.0,
      "statut": "PENDING",
      "montant_paye": 30000.0,
      "montant_restant": 62350.0,
      "latitude": 5.2804491,
      "longitude": -3.9469509,
      "photo_url": "https://fineract-waribei-transactions-154874852505.s3.eu-north-1.amazonaws.com/documents/07694c7c9afa90392a4d9e3b7aeec68e.jpg",
      "nb_tx_historique": 5.0,
      "comments": [
        {
          "date": "2026-06-23",
          "type": "GENERIC_COMMENT",
          "content": "Visite (Sortant) [Recouvrement] : il fera son remboursement le jeudi",
          "author": "KoneMasse"
        },
        {
          "date": "2026-06-22",
          "type": "COURIER",
          "content": "Date affichée : 2026-06-22 | Commune : Koumassi | Lieu : Soweto au bord | Montant total : 55800 | Avance : 80000 | Frais transaction : 3000 | Frais retard : 2800 | Montant payé : 30000",
          "author": "evinne"
        },
        {
          "date": "2026-06-22",
          "type": "COURIER",
          "content": "Date affichée : 2026-06-22 | Commune : Koumassi | Lieu : Soweto au bord | Montant total : 55800 | Avance : 80000 | Frais transaction : 3000 | Frais retard : 2800 | Montant payé : 30000",
          "author": "evinne"
        },
        {
          "date": "2026-06-18",
          "type": "GENERIC_COMMENT",
          "content": "Appel (Sortant) [Recouvrement] : jusqua samedi pour solder",
          "author": "evinne"
        },
        {
          "date": "2026-06-18",
          "type": "GENERIC_COMMENT",
          "content": "Appel (Sortant) [Recouvrement] : aucune reponse",
          "author": "evinne"
        },
        {
          "date": "2026-06-17",
          "type": "GENERIC_COMMENT",
          "content": "Appel (Sortant) [Recouvrement] :  va faire un versement aujourdhui",
          "author": "evinne"
        },
        {
          "date": "2026-06-16",
          "type": "GENERIC_COMMENT",
          "content": "Appel (Sortant) [Recouvrement] : va faire un versement aujourdhui",
          "author": "evinne"
        }
      ]
    },
    {
      "tx_id": 20235.0,
      "merchant_id": 2671.0,
      "merchant_name": "Gloria Ahounou",
      "district": "Bingerville",
      "phone": "2250564478055",
      "supplier_name": "La Cave du Marché",
      "montant": 50350.0,
      "date_achat": "2026-06-08",
      "maturity_date": "2026-06-15",
      "jours_retard": 9.0,
      "statut": "PENDING",
      "montant_paye": 0.0,
      "montant_restant": 50350.0,
      "latitude": 5.3498889,
      "longitude": -3.8779249,
      "photo_url": "https://fineract-waribei-transactions-154874852505.s3.eu-north-1.amazonaws.com/documents/f77bce5d70c6fdfe13c7c46625435cc5.jpg",
      "nb_tx_historique": 3.0,
      "comments": [
        {
          "date": "2026-06-22",
          "type": "GENERIC_COMMENT",
          "content": "Appel (Sortant) [Recouvrement] : Injoignable",
          "author": "evinne"
        },
        {
          "date": "2026-06-22",
          "type": "COURIER",
          "content": "Date affichée : 2026-06-22 | Commune : Bingerville | Lieu : Bingerville cité Impôt | Montant total : 53950 | Avance : 50000 | Frais transaction : 1500 | Frais retard : 2450 | Montant payé : 0",
          "author": "evinne"
        },
        {
          "date": "2026-06-17",
          "type": "GENERIC_COMMENT",
          "content": "Appel (Sortant) [Recouvrement] : aucune reponse",
          "author": "evinne"
        }
      ]
    },
    {
      "tx_id": 20177.0,
      "merchant_id": 2462.0,
      "merchant_name": "MONGUEHI EDWIGE",
      "district": "Adjamé",
      "phone": "+2250787292519",
      "supplier_name": "Sd Gonty Adjamé - liberté ",
      "montant": 40000.0,
      "date_achat": "2026-06-08",
      "maturity_date": "2026-06-15",
      "jours_retard": 9.0,
      "statut": "PENDING",
      "montant_paye": 0.0,
      "montant_restant": 40000.0,
      "latitude": 5.3679731,
      "longitude": -4.0236309,
      "photo_url": "https://fineract-waribei-transactions-154874852505.s3.eu-north-1.amazonaws.com/documents/8ebbf3095e73b1db2585cb92387e695f.jpg",
      "nb_tx_historique": 8.0,
      "comments": [
        {
          "date": "2026-06-22",
          "type": "COURIER",
          "content": "Date affichée : 2026-06-22 | Commune : Adjamé | Lieu : Willyamsville terminus 14 | Montant total : 33950 | Avance : 30000 | Frais transaction : 1500 | Frais retard : 2450 | Montant payé : 0",
          "author": "evinne"
        },
        {
          "date": "2026-06-22",
          "type": "GENERIC_COMMENT",
          "content": "Appel (Sortant) [Recouvrement] : aucune reponse",
          "author": "KoneMasse"
        },
        {
          "date": "2026-06-22",
          "type": "COURIER",
          "content": "Date affichée : 2026-06-22 | Commune : Adjamé | Lieu : Willyamsville terminus 14 | Montant total : 33950 | Avance : 30000 | Frais transaction : 1500 | Frais retard : 2450 | Montant payé : 0",
          "author": "evinne"
        },
        {
          "date": "2026-06-18",
          "type": "GENERIC_COMMENT",
          "content": "Appel (Sortant) [Recouvrement] : aucune reponse",
          "author": "evinne"
        },
        {
          "date": "2026-06-17",
          "type": "GENERIC_COMMENT",
          "content": "Appel (Sortant) [Recouvrement] : je vais faire  ca mmr",
          "author": "evinne"
        }
      ]
    },
    {
      "tx_id": 19839.0,
      "merchant_id": 1096.0,
      "merchant_name": "LEBE DJEZA VIVIANNE",
      "district": null,
      "phone": "+2250556140718",
      "supplier_name": "Sd el shaada ",
      "montant": 400000.0,
      "date_achat": "2026-06-02",
      "maturity_date": "2026-06-16",
      "jours_retard": 8.0,
      "statut": "PENDING",
      "montant_paye": 0.0,
      "montant_restant": 400000.0,
      "latitude": 5.2984345,
      "longitude": -3.969757,
      "photo_url": null,
      "nb_tx_historique": 19.0,
      "comments": [
        {
          "date": "2026-06-22",
          "type": "GENERIC_COMMENT",
          "content": "Appel (Sortant) [Recouvrement] : Injoignable",
          "author": "evinne"
        },
        {
          "date": "2026-06-19",
          "type": "GENERIC_COMMENT",
          "content": "Appel (Sortant) [Recouvrement] : Injoignable",
          "author": "evinne"
        },
        {
          "date": "2026-06-17",
          "type": "GENERIC_COMMENT",
          "content": "Appel (Sortant) [Recouvrement] : aucune reponse",
          "author": "evinne"
        }
      ]
    },
    {
      "tx_id": 19846.0,
      "merchant_id": 15.0,
      "merchant_name": "Rachel Nadege Djei",
      "district": null,
      "phone": "2250757041712",
      "supplier_name": "Cave de luxe",
      "montant": 399500.0,
      "date_achat": "2026-05-26",
      "maturity_date": "2026-06-16",
      "jours_retard": 8.0,
      "statut": "PENDING",
      "montant_paye": 202400.0,
      "montant_restant": 197100.0,
      "latitude": null,
      "longitude": null,
      "photo_url": null,
      "nb_tx_historique": 49.0,
      "comments": [
        {
          "date": "2026-06-22",
          "type": "GENERIC_COMMENT",
          "content": "Appel (Sortant) [Recouvrement] : aucune reponse",
          "author": "evinne"
        },
        {
          "date": "2026-06-17",
          "type": "GENERIC_COMMENT",
          "content": "Appel (Sortant) [Recouvrement] : je vais solder aujourdhui mr",
          "author": "evinne"
        }
      ]
    },
    {
      "tx_id": 20241.0,
      "merchant_id": 1375.0,
      "merchant_name": "YOHOU TAPE MICHEL",
      "district": null,
      "phone": "+2250707011949",
      "supplier_name": "Dépôt Francky",
      "montant": 168000.0,
      "date_achat": "2026-06-09",
      "maturity_date": "2026-06-16",
      "jours_retard": 8.0,
      "statut": "PENDING",
      "montant_paye": 125000.0,
      "montant_restant": 43000.0,
      "latitude": 5.4010177,
      "longitude": -3.9864639,
      "photo_url": null,
      "nb_tx_historique": 79.0,
      "comments": [
        {
          "date": "2026-06-22",
          "type": "GENERIC_COMMENT",
          "content": "Appel (Sortant) [Recouvrement] : aucune reponse",
          "author": "evinne"
        },
        {
          "date": "2026-06-18",
          "type": "GENERIC_COMMENT",
          "content": "Appel (Sortant) [Recouvrement] : un versement aujourdhui",
          "author": "evinne"
        },
        {
          "date": "2026-06-17",
          "type": "GENERIC_COMMENT",
          "content": "Appel (Sortant) [Recouvrement] : un versement aujourdhui",
          "author": "evinne"
        }
      ]
    },
    {
      "tx_id": 20244.0,
      "merchant_id": 2563.0,
      "merchant_name": "GOGOUA EMMANUELLA SUZANNE",
      "district": "Yopougon",
      "phone": "2250748185313",
      "supplier_name": "NCDI.S ",
      "montant": 62450.0,
      "date_achat": "2026-06-09",
      "maturity_date": "2026-06-16",
      "jours_retard": 8.0,
      "statut": "PENDING",
      "montant_paye": 28600.0,
      "montant_restant": 33850.0,
      "latitude": null,
      "longitude": null,
      "photo_url": "https://fineract-waribei-transactions-154874852505.s3.eu-north-1.amazonaws.com/documents/46eebe0ce8fd32727c78d2900608c729.jpg",
      "nb_tx_historique": 1.0,
      "comments": [
        {
          "date": "2026-06-22",
          "type": "GENERIC_COMMENT",
          "content": "Appel (Sortant) [Recouvrement] : jai fait un versement aujourdhui",
          "author": "evinne"
        },
        {
          "date": "2026-06-18",
          "type": "GENERIC_COMMENT",
          "content": "Appel (Sortant) [Recouvrement] : aucune reponse",
          "author": "evinne"
        },
        {
          "date": "2026-06-17",
          "type": "GENERIC_COMMENT",
          "content": "Appel (Sortant) [Recouvrement] : aucune reponse",
          "author": "evinne"
        }
      ]
    }
  ]
}